wetai/__init__.py
wetai/test.py
wetai-0.0.1.dist-info/LICENSE
wetai-0.0.1.dist-info/METADATA
wetai-0.0.1.dist-info/WHEEL
wetai-0.0.1.dist-info/top_level.txt
wetai-0.0.1.dist-info/RECORD
