Metadata-Version: 2.1
Name: wetai
Version: 0.0.1
Summary: wetAI Python utilities
Home-page: https://github.com/braingeneers/wetai
Author: Braingeneers
License: UNKNOWN
Keywords: machine-learning,jupyter,neuroscience,wetai,braingeneers
Platform: UNKNOWN
Classifier: Development Status :: 1 - Planning
Classifier: Intended Audience :: Science/Research
Classifier: Programming Language :: Python :: 3
Classifier: License :: OSI Approved :: MIT License
Requires-Dist: numpy
Requires-Dist: scipy
Requires-Dist: requests
